geomesher/__init__.py
geomesher/area_weighted.py
geomesher/common.py
geomesher/exceptions.py
geomesher/fields.py
geomesher/geometry.py
geomesher/mesher.py
geomesher/py.typed
geomesher-0.1.0.dist-info/LICENSE
geomesher-0.1.0.dist-info/METADATA
geomesher-0.1.0.dist-info/WHEEL
geomesher-0.1.0.dist-info/top_level.txt
geomesher-0.1.0.dist-info/RECORD
