Metadata-Version: 2.1
Name: geomesher
Version: 0.1.0
Summary: Meshing a GeoDataFrame using Gmsh.
Maintainer-email: Taher Chegini <cheginit@gmail.com>
License: MIT
Project-URL: Code, https://github.com/deltares/geomesher
Project-URL: Home, https://github.com/deltares/geomesher
Project-URL: Issues, https://github.com/deltares/geomesher/issues
Keywords: geopandas,mesh,unstructured grid
Platform: any
Classifier: Development Status :: 3 - Alpha
Classifier: Intended Audience :: Science/Research
Classifier: License :: OSI Approved :: MIT License
Classifier: Operating System :: OS Independent
Classifier: Programming Language :: Python
Classifier: Programming Language :: Python :: 3 :: Only
Classifier: Programming Language :: Python :: 3.8
Classifier: Programming Language :: Python :: 3.9
Classifier: Programming Language :: Python :: 3.10
Classifier: Programming Language :: Python :: 3.11
Classifier: Topic :: Scientific/Engineering
Requires-Python: >=3.8
License-File: LICENSE
Requires-Dist: geopandas
Requires-Dist: gmsh
Requires-Dist: numpy >=1.21
Requires-Dist: pandas
Requires-Dist: scipy
Requires-Dist: shapely >=2
Provides-Extra: test
Requires-Dist: coverage[toml] ; extra == 'test'
Requires-Dist: pytest-cov ; extra == 'test'
Requires-Dist: pytest-xdist[psutil] ; extra == 'test'
